pptstab/models/aac_model/ann_model.onnx
pptstab/models/aac_model/keras_metadata.pb
pptstab/models/aac_model/mlp_regressor.pkl
pptstab/models/aac_model/saved_model.pb
pptstab/models/aac_model/variables/variables.data-00000-of-00001
pptstab/models/aac_model/variables/variables.index
pptstab/models/emb_model/ann_model.onnx
pptstab/models/emb_model/fingerprint.pb
pptstab/models/emb_model/keras_metadata.pb
pptstab/models/emb_model/mlp_regressor.pkl
pptstab/models/emb_model/saved_model.pb
pptstab/models/emb_model/variables/variables.data-00000-of-00001
pptstab/models/emb_model/variables/variables.index
pptstab/models/ser_model/ann_model.onnx
pptstab/models/ser_model/fingerprint.pb
pptstab/models/ser_model/keras_metadata.pb
pptstab/models/ser_model/mlp_regressor.pkl
pptstab/models/ser_model/saved_model.pb
pptstab/models/ser_model/variables/variables.data-00000-of-00001
pptstab/models/ser_model/variables/variables.index
pptstab/python_script/__init__.py
pptstab/python_script/pptstab.py
pptstab-1.0.1.dist-info/METADATA
pptstab-1.0.1.dist-info/WHEEL
pptstab-1.0.1.dist-info/entry_points.txt
pptstab-1.0.1.dist-info/top_level.txt
pptstab-1.0.1.dist-info/RECORD
