Metadata-Version: 2.1
Name: pptstab
Version: 1.0.1
Summary: PPTStab: Designing of thermostable proteins with a desired melting temperature
Home-page: https://github.com/raghavalab/pptstab
Author: G.P.S. Raghava
Author-email: raghava@iiitd.ac.in
Requires-Python: >=3.6
Requires-Dist: numpy
Requires-Dist: pandas
Requires-Dist: joblib
Requires-Dist: tqdm
Requires-Dist: torch
Requires-Dist: onnxruntime
Requires-Dist: tensorflow
Requires-Dist: scikit-learn
Requires-Dist: transformers
